botocache/botocache.py
botocache-0.0.6.dist-info/METADATA
botocache-0.0.6.dist-info/WHEEL
botocache-0.0.6.dist-info/RECORD
