Metadata-Version: 2.1
Name: botocache
Version: 0.0.6
Summary: Caching for Boto and Boto3 SDK
Author: rams3sh
Requires-Python: >=3.8
Classifier: Programming Language :: Python :: 3
Classifier: Programming Language :: Python :: 3.8
Classifier: Programming Language :: Python :: 3.9
Classifier: Programming Language :: Python :: 3.10
Classifier: Programming Language :: Python :: 3.11
Classifier: Programming Language :: Python :: 3.12
Requires-Dist: botocore (>=1.34.61,<2.0.0)
Requires-Dist: cachetools (==5.3.3)
